pyned2lla-0.1.1.dist-info/METADATA
pyned2lla-0.1.1.dist-info/WHEEL
pyned2lla.libs/libgcc_s-b5472b99.so.1
pyned2lla/__init__.py
pyned2lla/pyned2lla.pypy39-pp73-x86-linux-gnu.so
pyned2lla-0.1.1.dist-info/RECORD
