Metadata-Version: 2.4
Name: pyned2lla
Version: 0.1.1
Classifier: Development Status :: 5 - Production/Stable
Classifier: Intended Audience :: Developers
Classifier: License :: OSI Approved :: MIT License
Classifier: Programming Language :: Rust
Classifier: Programming Language :: Python :: Implementation :: CPython
Classifier: Programming Language :: Python :: Implementation :: PyPy
Summary: NED (North East Down) to LLA (Latitude Longitude Altitude) conversion for Python
Author: Andrew Straw <strawman@astraw.com>
Author-email: Andrew Straw <strawman@astraw.com>
License: MIT
Requires-Python: >=3.8
Project-URL: Homepage, https://github.com/strawlab/pyned2lla
